chebai_graph/__init__.py
chebai_graph/loss/__init__.py
chebai_graph/loss/pretraining.py
chebai_graph/models/__init__.py
chebai_graph/models/augmented.py
chebai_graph/models/base.py
chebai_graph/models/dynamic_gni.py
chebai_graph/models/gat.py
chebai_graph/models/gin_net.py
chebai_graph/models/graph.py
chebai_graph/models/resgated.py
chebai_graph/preprocessing/__init__.py
chebai_graph/preprocessing/collate.py
chebai_graph/preprocessing/property_encoder.py
chebai_graph/preprocessing/structures.py
chebai_graph/preprocessing/transform_unlabeled.py
chebai_graph/preprocessing/bin/AtomCharge/indices_one_hot.txt
chebai_graph/preprocessing/bin/AtomFunctionalGroup/indices_one_hot.txt
chebai_graph/preprocessing/bin/AtomHybridization/indices_one_hot.txt
chebai_graph/preprocessing/bin/AtomNodeLevel/indices_one_hot.txt
chebai_graph/preprocessing/bin/AtomNumHs/indices_one_hot.txt
chebai_graph/preprocessing/bin/AtomType/indices_one_hot.txt
chebai_graph/preprocessing/bin/BondLevel/indices_one_hot.txt
chebai_graph/preprocessing/bin/BondType/indices_one_hot.txt
chebai_graph/preprocessing/bin/NumAtomBonds/indices_one_hot.txt
chebai_graph/preprocessing/datasets/__init__.py
chebai_graph/preprocessing/datasets/chebi.py
chebai_graph/preprocessing/datasets/pubchem.py
chebai_graph/preprocessing/datasets/utils.py
chebai_graph/preprocessing/fg_detection/__init__.py
chebai_graph/preprocessing/fg_detection/fg_aware_rule_based.py
chebai_graph/preprocessing/fg_detection/fg_constants.py
chebai_graph/preprocessing/properties/__init__.py
chebai_graph/preprocessing/properties/augmented_properties.py
chebai_graph/preprocessing/properties/base.py
chebai_graph/preprocessing/properties/constants.py
chebai_graph/preprocessing/properties/properties.py
chebai_graph/preprocessing/reader/__init__.py
chebai_graph/preprocessing/reader/augmented_reader.py
chebai_graph/preprocessing/reader/reader.py
chebai_graph/preprocessing/reader/static_gni.py
chebai_graph-1.0.0.dist-info/entry_points.txt
chebai_graph-1.0.0.dist-info/WHEEL
chebai_graph-1.0.0.dist-info/METADATA
chebai_graph-1.0.0.dist-info/RECORD
