Metadata-Version: 2.4
Name: chebai-graph
Version: 1.0.0
Summary: GNNs for ChEB-AI
Author-email: Martin Glauer <martin.glauer@ovgu.de>
Requires-Python: >=3.8
Requires-Dist: chebai
Requires-Dist: descriptastorus
Requires-Dist: tox ; extra == "dev"
Requires-Dist: isort ; extra == "linters"
Requires-Dist: pre-commit ; extra == "linters"
Requires-Dist: black ; extra == "linters"
Provides-Extra: dev
Provides-Extra: linters
